README.md
setup.py
tc_etl_lib/__init__.py
tc_etl_lib/auth.py
tc_etl_lib/cb.py
tc_etl_lib/exceptions.py
tc_etl_lib/iota.py
tc_etl_lib/normalizer.py
tc_etl_lib/store.py
tc_etl_lib/test_iota.py
tc_etl_lib/test_normalizer.py
tc_etl_lib/test_store.py
tc_etl_lib.egg-info/PKG-INFO
tc_etl_lib.egg-info/SOURCES.txt
tc_etl_lib.egg-info/dependency_links.txt
tc_etl_lib.egg-info/requires.txt
tc_etl_lib.egg-info/top_level.txt