Metadata-Version: 2.1
Name: tc-etl-lib
Version: 0.12.0
Summary: Librería común para uso en ETL
Home-page: 
Author: 
Author-email: 
